fonts/Beleren2016-Bold.ttf
mtgbinderspine/client.py
mtgbinderspine/main.py
mtgbinderspine/render.py
mtgbinderspine/util.py
mtgbinderspine-0.1.3.dist-info/entry_points.txt
mtgbinderspine-0.1.3.dist-info/WHEEL
mtgbinderspine-0.1.3.dist-info/METADATA
mtgbinderspine-0.1.3.dist-info/RECORD
